linuxinfo/__init__.py
linuxinfo/helpers.py
linuxinfo/linux.py
linuxinfo/rpi.py
linuxinfo-0.1.1.dist-info/LICENSE
linuxinfo-0.1.1.dist-info/WHEEL
linuxinfo-0.1.1.dist-info/METADATA
linuxinfo-0.1.1.dist-info/RECORD
