Metadata-Version: 2.1
Name: linuxinfo
Version: 0.1.1
Summary: A python library to get linux/raspberry pi info
Home-page: https://pypi.org/project/linuxinfo/
License: MIT
Keywords: raspberry pi,pi,info,proc,cpu,linux
Author: walchko
Author-email: walchko@users.noreply.github.com
Requires-Python: >=3.6
Classifier: Development Status :: 4 - Beta
Classifier: Intended Audience :: Developers
Classifier: License :: OSI Approved :: MIT License
Classifier: Operating System :: OS Independent
Classifier: Programming Language :: Python :: 3
Classifier: Programming Language :: Python :: 3.6
Classifier: Programming Language :: Python :: 3.7
Classifier: Programming Language :: Python :: 3.8
Classifier: Topic :: Software Development :: Libraries
Classifier: Topic :: Software Development :: Libraries :: Application Frameworks
Classifier: Topic :: Software Development :: Libraries :: Python Modules
Requires-Dist: importlib-metadata
Project-URL: Repository, http://github.com/MomsFriendlyRobotCompany/linuxinfo
